{
  "chainId": 13939,
  "chainName": "Reef Testnet",
  "rpcUrl": "http://127.0.0.1:8545",
  "deployer": "0x6dAcaE67EC045B86De16a224b6f27EaC1b047572",
  "generatedAt": "2026-04-09T16:41:41.561Z",
  "probe": {
    "verified": true,
    "address": "0x9ff870802be2b769fa4eae4f61b85cf273725760",
    "txHash": "0xda93a3afb9974de86012047ff82d3790c2176fce58dcfa7444014dd7a81b902f",
    "blockNumber": 14,
    "reason": "Reef returned bytecode for the deployment probe."
  },
  "contracts": {
    "official": {
      "seaport": {
        "address": "0x8fC9Fe992499cDAa7dF14025f3ADaE385272D8C4",
        "verified": false
      },
      "conduitController": {
        "address": "0xEC163d04A56A4592D9EbFBF42aE9eb5aB5161F0E",
        "verified": false
      },
      "seaDrop": {
        "address": "",
        "verified": false
      },
      "creatorFactory": {
        "address": "",
        "verified": false
      },
      "collectionImplementation": {
        "address": "",
        "verified": false
      }
    },
    "fallback": {
      "creatorFactory721": {
        "address": "0x31dc26025d6311e47e43afcc37beb45d49eac33a",
        "verified": true,
        "deploymentTxHash": "0x15f488bca322d24b75a8938e5631583d67665e2e1a506017b8b525a7f6cd55cc",
        "blockNumber": 15
      },
      "editionFactory1155": {
        "address": "0x75b1ab2b755678d53f3c1ddd7b380941b0b65dc1",
        "verified": true,
        "deploymentTxHash": "0x481ddb5446f6ee0566df6127d9a92d5934ad4b492d86b4cb7b88c09e2e92df1e",
        "blockNumber": 16
      },
      "marketplace721": {
        "address": "0x628e09153dbacfb0a4aa7cef0a80c2046019ffb2",
        "verified": true,
        "deploymentTxHash": "0xe2776f8803458b6a1859e1052bc450118a76c9647e533de285fe120c7ff665db",
        "blockNumber": 17
      },
      "marketplace1155": {
        "address": "0x5e9d035a4502c1bfa25f1f51fa7bcab2c2d9c1b2",
        "verified": true,
        "deploymentTxHash": "0xc17ea33cbb039a3277264def649b361c111d5d0e40313389f7dcac822fdbdbb2",
        "blockNumber": 18
      },
      "dropManager": {
        "address": "0xc1d2d590f329a05660b20e0a36add9d6fc851c84",
        "verified": true,
        "deploymentTxHash": "0x9f5e75b52360c268033229335bb49c02840af97716216c3a7385d0d44a6268e1",
        "blockNumber": 19
      }
    }
  },
  "deployment": {
    "mode": "fallback",
    "creator": {
      "erc721": {
        "enabled": true,
        "mode": "fallback",
        "factoryAddress": "0x31dc26025d6311e47e43afcc37beb45d49eac33a",
        "implementationAddress": "",
        "marketplaceMode": "fallback",
        "reason": ""
      },
      "erc1155": {
        "enabled": true,
        "mode": "fallback",
        "factoryAddress": "0x75b1ab2b755678d53f3c1ddd7b380941b0b65dc1",
        "implementationAddress": "",
        "marketplaceMode": "fallback",
        "reason": ""
      }
    },
    "marketplace": {
      "erc721": {
        "enabled": true,
        "mode": "fallback",
        "address": "0x628e09153dbacfb0a4aa7cef0a80c2046019ffb2",
        "reason": ""
      },
      "erc1155": {
        "enabled": true,
        "mode": "fallback",
        "address": "0x5e9d035a4502c1bfa25f1f51fa7bcab2c2d9c1b2",
        "reason": ""
      }
    }
  },
  "errors": []
}